hypnotic.py
hypnotic-0.1.2.dist-info/licenses/LICENSE
hypnotic-0.1.2.dist-info/METADATA
hypnotic-0.1.2.dist-info/WHEEL
hypnotic-0.1.2.dist-info/entry_points.txt
hypnotic-0.1.2.dist-info/top_level.txt
hypnotic-0.1.2.dist-info/RECORD
