Metadata-Version: 2.4
Name: hypnotic
Version: 0.1.2
Summary: A programming language that doesn't scream at you. Phonetic shortcuts, forgiving syntax, zero indentation fascism.
Author: hypnotIC
License: MIT
Project-URL: Homepage, https://github.com/zachseven/hypnotic
Project-URL: Repository, https://github.com/zachseven/hypnotic
Project-URL: Issues, https://github.com/zachseven/hypnotic/issues
Keywords: programming-language,interpreter,esoteric,fun
Classifier: Development Status :: 4 - Beta
Classifier: Environment :: Console
Classifier: Intended Audience :: Developers
Classifier: Intended Audience :: Education
Classifier: License :: OSI Approved :: MIT License
Classifier: Operating System :: OS Independent
Classifier: Programming Language :: Python :: 3
Classifier: Programming Language :: Python :: 3.8
Classifier: Programming Language :: Python :: 3.9
Classifier: Programming Language :: Python :: 3.10
Classifier: Programming Language :: Python :: 3.11
Classifier: Programming Language :: Python :: 3.12
Classifier: Topic :: Software Development :: Interpreters
Requires-Python: >=3.8
License-File: LICENSE
Dynamic: license-file
